README.rst
setup.py
s3bro/__init__.py
s3bro/cli.py
s3bro/pool_map.py
s3bro/ratelimit.py
s3bro/s3_encryption.py
s3bro/s3_permission.py
s3bro/s3_permission_v2.py
s3bro/s3_purge.py
s3bro/s3_restore.py
s3bro/s3_tail.py
s3bro.egg-info/PKG-INFO
s3bro.egg-info/SOURCES.txt
s3bro.egg-info/dependency_links.txt
s3bro.egg-info/entry_points.txt
s3bro.egg-info/requires.txt
s3bro.egg-info/top_level.txt