Metadata-Version: 1.0
Name: s3bro
Version: 2.6
Summary: UNKNOWN
Home-page: https://github.com/rsavordelli/s3bro
Author: Rubem de Lima Savordelli
Author-email: rsavordelli@gmail.com
License: UNKNOWN
Platform: UNKNOWN
